README.md
setup.py
atd_emailutil.egg-info/PKG-INFO
atd_emailutil.egg-info/SOURCES.txt
atd_emailutil.egg-info/dependency_links.txt
atd_emailutil.egg-info/requires.txt
atd_emailutil.egg-info/top_level.txt
emailutil/__init__.py
emailutil/emailutil.py