Metadata-Version: 2.1
Name: atd-emailutil
Version: 0.0.1
Summary: Python utilities for sending emails with a gmail account.
Home-page: https://github.com/cityofaustin/atd-data-utils-email
Author: City of Austin
Author-email: transportation.data@austintexas.gov
License: UNKNOWN
Platform: UNKNOWN
Classifier: Programming Language :: Python :: 3
Classifier: License :: Public Domain
Classifier: Operating System :: OS Independent
Classifier: Development Status :: 4 - Beta
